extra_keras_datasets/__init__.py
extra_keras_datasets/emnist.py
extra_keras_datasets/iris.py
extra_keras_datasets/kmnist.py
extra_keras_datasets/stl10.py
extra_keras_datasets/svhn.py
extra_keras_datasets/usps.py
extra_keras_datasets/wine_quality.py
extra_keras_datasets-1.2.0.dist-info/LICENSE
extra_keras_datasets-1.2.0.dist-info/METADATA
extra_keras_datasets-1.2.0.dist-info/WHEEL
extra_keras_datasets-1.2.0.dist-info/top_level.txt
extra_keras_datasets-1.2.0.dist-info/RECORD
